{
  "company": "LTIMindtree",
  "quarter": "Q2",
  "fiscal_year": "FY26",
  "metrics": [
    {
      "heading": "Overall Mood",
      "phrase": "LTI Mindtree's outlook is very optimistic, scoring 78 out of 100.",
      "value": 78,
      "label": "Thriving"
    },
    {
      "heading": "Company Outlook",
      "phrase": "They see a promising future ahead with a score of 40.",
      "value": 40,
      "label": "Promising"
    },
    {
      "heading": "Sustainability",
      "phrase": "The company rates its sustainability practices as 'Very Clean' at 80.",
      "value": 80,
      "label": "Very Clean"
    },
    {
      "heading": "Environmental",
      "phrase": "Its environmental efforts are rated 'Green' at 75.",
      "value": 75,
      "label": "Green"
    },
    {
      "heading": "People & Society",
      "phrase": "LTI Mindtree scores its people and society impact as 'Excellent' with a rating of 80.",
      "value": 80,
      "label": "Excellent"
    },
    {
      "heading": "Corporate Governance",
      "phrase": "Management considers their governance practices to be 'Very Strong', scoring 85.",
      "value": 85,
      "label": "Very Strong"
    },
    {
      "heading": "Management Honesty",
      "phrase": "They rate management transparency as 'Very Open' at 80.",
      "value": 80,
      "label": "Very Open"
    },
    {
      "heading": "Financial Health",
      "phrase": "The company's financial health is rated 'Excellent' with a score of 94.",
      "value": 94,
      "label": "Excellent"
    },
    {
      "heading": "Growth Plans",
      "phrase": "Their growth plans are seen as very ambitious, getting a score of 93.",
      "value": 93,
      "label": "Very Ambitious"
    },
    {
      "heading": "Risk Level",
      "phrase": "Despite some risks, LTI Mindtree rates its risk level as 'Low Risk', scoring 28.",
      "value": 28,
      "label": "Low Risk"
    },
    {
      "heading": "Investor Confidence",
      "phrase": "Investors rate their trust in the company as 'Very Trusted' with a score of 83.",
      "value": 83,
      "label": "Very Trusted"
    }
  ],
  "_output_path": "LTIMindtree\\Q2_FY26"
}