{
  "company": "Adani Ports and SEZ",
  "quarter": "Q4",
  "fiscal_year": "FY25",
  "metrics": [
    {
      "heading": "Overall Mood",
      "phrase": "Adani Ports sounds very positive about their future prospects.",
      "value": 89,
      "label": "Thriving"
    },
    {
      "heading": "Company Outlook",
      "phrase": "",
      "value": 40,
      "label": "Promising"
    },
    {
      "heading": "Sustainability",
      "phrase": "",
      "value": 76,
      "label": "Clean"
    },
    {
      "heading": "Environmental",
      "phrase": "",
      "value": 75,
      "label": "Green"
    },
    {
      "heading": "People & Society",
      "phrase": "",
      "value": 70,
      "label": "Good"
    },
    {
      "heading": "Corporate Governance",
      "phrase": "",
      "value": 80,
      "label": "Very Strong"
    },
    {
      "heading": "Management Honesty",
      "phrase": "",
      "value": 85,
      "label": "Very Open"
    },
    {
      "heading": "Financial Health",
      "phrase": "",
      "value": 94,
      "label": "Excellent"
    },
    {
      "heading": "Growth Plans",
      "phrase": "",
      "value": 91,
      "label": "Very Ambitious"
    },
    {
      "heading": "Risk Level",
      "phrase": "",
      "value": 75,
      "label": "Very Safe"
    },
    {
      "heading": "Investor Confidence",
      "phrase": "",
      "value": 92,
      "label": "Very Trusted"
    }
  ],
  "_output_path": "Adani_Ports_and_SEZ\\Q4_FY25"
}