{
  "doc_meta": {
    "doc_id": "66be13992e3b",
    "stock": "ONGC",
    "doc_type": "ec",
    "period": "NOV25",
    "quarter": null,
    "fiscal_year": "FY26",
    "filename": "NOV25.pdf",
    "file_path": "data/ONGC/EC/NOV25.pdf"
  },
  "doc_type": "ec",
  "sections": {
    "financial_metrics": {
      "section": "financial_metrics",
      "title": "Financial Metrics",
      "score": 84.5,
      "label": "Excellent",
      "bullets": [
        "The company made more money than expected because its smaller parts did really well.",
        "Even though some areas didn't do as well, they're still investing in future growth."
      ]
    },
    "risk_intelligence": {
      "section": "risk_intelligence",
      "title": "Risk Intelligence",
      "score": 74.3,
      "label": "Low Risk",
      "bullets": [
        "The company faces challenges due to political issues in some countries, which could affect its operations.",
        "Oil production is lower than expected, and falling oil prices have reduced profits, with no clear plan to handle these issues."
      ]
    },
    "esg": {
      "section": "esg",
      "title": "ESG Analysis",
      "score": 75.0,
      "label": "Good",
      "bullets": [
        "The company is doing well in taking care of the environment.",
        "They have good practices in place to reduce their impact on nature."
      ]
    },
    "speaker_sentiment": {
      "section": "speaker_sentiment",
      "title": "Speaker Sentiment",
      "score": 78.6,
      "label": "Good",
      "bullets": [
        "The company leaders talked about current problems but are hopeful things will get better soon.",
        "They explained why they faced issues and seemed positive about fixing them in the future."
      ]
    },
    "qa_transparency": {
      "section": "qa_transparency",
      "title": "Q&A Transparency",
      "score": 18.6,
      "label": "Very Poor",
      "bullets": [
        "The company often gave numbers but didn't explain their plans clearly.",
        "They admitted problems but didn't say how or when they would fix them."
      ]
    },
    "overall_sentiment": {
      "section": "overall_sentiment",
      "title": "Overall Sentiment",
      "score": 11.5,
      "label": "Very Poor",
      "bullets": [
        "The company is facing challenges because lower oil prices have hurt its financial performance.",
        "While there are some positive changes, the company is still cautious about future risks."
      ]
    },
    "investment_synthesis": {
      "section": "investment_synthesis",
      "title": "Investment Synthesis",
      "score": 50,
      "label": "Average",
      "bullets": [
        "The company's overall profit went up because its smaller companies did really well, even though its main business made less money.",
        "They are investing in new projects to find more oil and gas, which should help them grow in the future despite current challenges."
      ]
    }
  }
}