{
  "doc_meta": {
    "doc_id": "2cc8f43bec9e",
    "stock": "Interglobe Aviation",
    "doc_type": "ec",
    "period": "AUG25",
    "quarter": null,
    "fiscal_year": "FY26",
    "filename": "AUG25.pdf",
    "file_path": "data/Interglobe Aviation/EC/AUG25.pdf"
  },
  "doc_type": "ec",
  "sections": {
    "financial_metrics": {
      "section": "financial_metrics",
      "title": "Financial Metrics",
      "score": 94.2,
      "label": "Excellent",
      "bullets": [
        "The company did well financially because more people chose to fly with them.",
        "Even with global issues affecting profits, they still have enough money and are planning for future growth."
      ]
    },
    "risk_intelligence": {
      "section": "risk_intelligence",
      "title": "Risk Intelligence",
      "score": 94.8,
      "label": "Well Managed",
      "bullets": [
        "The company is handling risks well despite challenges like geopolitical tensions and flight disruptions.",
        "Fuel costs have been lower, helping the company, but unpredictable prices could still be a problem."
      ]
    },
    "esg": {
      "section": "esg",
      "title": "ESG Analysis",
      "score": 47.5,
      "label": "Average",
      "bullets": [
        "The company is doing okay in taking care of social issues like community and employee relations.",
        "There is room for improvement in how the company is managed and makes decisions."
      ]
    },
    "speaker_sentiment": {
      "section": "speaker_sentiment",
      "title": "Speaker Sentiment",
      "score": 96.1,
      "label": "Excellent",
      "bullets": [
        "The company's leaders spoke with confidence about their plans and ability to handle challenges.",
        "They consistently showed a positive attitude, even when faced with tough questions from analysts."
      ]
    },
    "qa_transparency": {
      "section": "qa_transparency",
      "title": "Q&A Transparency",
      "score": 46.7,
      "label": "Average",
      "bullets": [
        "The company gave clear answers about their plans and assets, but not about market demand.",
        "They were not very detailed when predicting future performance, which makes it hard to fully understand their outlook."
      ]
    },
    "overall_sentiment": {
      "section": "overall_sentiment",
      "title": "Overall Sentiment",
      "score": 84.6,
      "label": "Excellent",
      "bullets": [
        "The company is doing well and expects to improve even more in the future.",
        "There are some challenges, but the company is handling them and planning carefully."
      ]
    },
    "investment_synthesis": {
      "section": "investment_synthesis",
      "title": "Investment Synthesis",
      "score": 75,
      "label": "Good",
      "bullets": [
        "IndiGo is doing well by making more money and keeping customers happy, even with tough challenges.",
        "The airline is planning for future growth by buying new planes and expanding its international reach."
      ]
    }
  }
}