{
  "doc_meta": {
    "doc_id": "359fb47bfb32",
    "stock": "NTPC",
    "doc_type": "ec",
    "period": "NOV25",
    "quarter": null,
    "fiscal_year": "FY26",
    "filename": "NOV25.pdf",
    "file_path": "data/NTPC/EC/NOV25.pdf"
  },
  "doc_type": "ec",
  "sections": {
    "financial_metrics": {
      "section": "financial_metrics",
      "title": "Financial Metrics",
      "score": 95.7,
      "label": "Excellent",
      "bullets": [
        "The company is doing well because its renewable energy part is growing strongly.",
        "They are spending a lot to expand, which shows confidence in future growth."
      ]
    },
    "risk_intelligence": {
      "section": "risk_intelligence",
      "title": "Risk Intelligence",
      "score": 94.4,
      "label": "Well Managed",
      "bullets": [
        "The company is handling risks well, but there are challenges like regulatory issues that could affect how efficiently they operate.",
        "Their coal supply is stable for now, but any supply problems or higher demand could disrupt their operations."
      ]
    },
    "esg": {
      "section": "esg",
      "title": "ESG Analysis",
      "score": 70.0,
      "label": "Good",
      "bullets": [
        "The company is doing well in taking care of the environment.",
        "There is room for improvement in how the company is managed and run."
      ]
    },
    "speaker_sentiment": {
      "section": "speaker_sentiment",
      "title": "Speaker Sentiment",
      "score": 93.5,
      "label": "Excellent",
      "bullets": [
        "The company's leaders spoke with confidence about their plans and future growth.",
        "They have strong projects lined up and believe they can handle any challenges well."
      ]
    },
    "qa_transparency": {
      "section": "qa_transparency",
      "title": "Q&A Transparency",
      "score": 48.5,
      "label": "Average",
      "bullets": [
        "The company is clear about its day-to-day operations but less so about its long-term plans.",
        "They are good at giving numbers and timelines for some things, but not for everything."
      ]
    },
    "overall_sentiment": {
      "section": "overall_sentiment",
      "title": "Overall Sentiment",
      "score": 96.0,
      "label": "Excellent",
      "bullets": [
        "The company is doing well with renewable energy and plans to grow even more.",
        "Despite some weather-related challenges, the company is set to benefit from India's growing economy."
      ]
    },
    "investment_synthesis": {
      "section": "investment_synthesis",
      "title": "Investment Synthesis",
      "score": 75,
      "label": "Good",
      "bullets": [
        "The company is expanding in renewable energy, which is good because more people need power as industries grow.",
        "There are some risks like weather affecting demand and high costs for expansion, but the company is still doing well overall."
      ]
    }
  }
}