{
  "company": "HDFC Life",
  "quarter": "Q1",
  "fiscal_year": "FY26",
  "metrics": [
    {
      "heading": "Overall Mood",
      "phrase": "The overall mood is positive at 58 out of 100.",
      "value": 58,
      "label": "Doing Well"
    },
    {
      "heading": "Company Outlook",
      "phrase": "",
      "value": 40,
      "label": "Promising"
    },
    {
      "heading": "Sustainability",
      "phrase": "",
      "value": 54,
      "label": "Mixed"
    },
    {
      "heading": "Environmental",
      "phrase": "",
      "value": 0,
      "label": "Very Polluting"
    },
    {
      "heading": "People & Society",
      "phrase": "",
      "value": 70,
      "label": "Good"
    },
    {
      "heading": "Corporate Governance",
      "phrase": "",
      "value": 85,
      "label": "Very Strong"
    },
    {
      "heading": "Management Honesty",
      "phrase": "",
      "value": 75,
      "label": "Open"
    },
    {
      "heading": "Financial Health",
      "phrase": "",
      "value": 94,
      "label": "Excellent"
    },
    {
      "heading": "Growth Plans",
      "phrase": "",
      "value": 91,
      "label": "Very Ambitious"
    },
    {
      "heading": "Risk Level",
      "phrase": "",
      "value": -83,
      "label": "Danger Zone"
    },
    {
      "heading": "Investor Confidence",
      "phrase": "",
      "value": 93,
      "label": "Very Trusted"
    }
  ],
  "_output_path": "HDFC_Life\\Q1_FY26"
}